docs/index.md
docs/songbirdcore/common.md
docs/songbirdcore/gdrive.md
docs/songbirdcore/itunes.md
docs/songbirdcore/web.md
docs/songbirdcore/youtube.md
docs/songbirdcore/models/itunes_api.md
docs/songbirdcore/models/modes.md
songbirdcore/common.py
songbirdcore/gdrive.py
songbirdcore/itunes.py
songbirdcore/requirements.txt
songbirdcore/requirements.txt.blank
songbirdcore/test.txt
songbirdcore/version.py
songbirdcore/web.py
songbirdcore/youtube.py
songbirdcore/models/itunes_api.py
songbirdcore/models/modes.py
songbirdcore-0.1.6.dist-info/licenses/LICENSE
tests/unit/test_common.py
tests/unit/test_gdrive.py
tests/unit/test_itunes.py
tests/unit/test_web.py
tests/unit/test_youtube.py
tests/unit/resources/empty.m4a
tests/unit/resources/empty.mp3
tests/unit/resources/mock-itunes-lib/artist0/album/empty.m4a
tests/unit/resources/mock-itunes-lib/artist1/album/empty.mp3
tests/unit/resources/mock-itunes-lib/dolly parton/album/jolene.mp3
tests/unit/resources/mock-itunes-lib/pentatonix/album/jolene.mp3
songbirdcore-0.1.6.dist-info/METADATA
songbirdcore-0.1.6.dist-info/WHEEL
songbirdcore-0.1.6.dist-info/top_level.txt
songbirdcore-0.1.6.dist-info/RECORD
