Metadata-Version: 2.4
Name: songbirdcore
Version: 0.1.6
Summary: core low level api for songbird
Author: Christian Boin
Requires-Python: >=3.11
License-File: LICENSE
Requires-Dist: annotated-types==0.7.0
Requires-Dist: beautifulsoup4==4.12.3
Requires-Dist: brotli==1.2.0
Requires-Dist: cachetools==6.2.1
Requires-Dist: certifi==2024.12.14
Requires-Dist: charset-normalizer==3.4.0
Requires-Dist: cssselect==1.2.0
Requires-Dist: deprecation==2.1.0
Requires-Dist: eyeD3==0.9.8
Requires-Dist: fake-useragent==2.0.3
Requires-Dist: filetype==1.2.0
Requires-Dist: google-api-core==2.28.1
Requires-Dist: google-api-python-client==2.187.0
Requires-Dist: google-auth==2.41.1
Requires-Dist: google-auth-httplib2==0.2.1
Requires-Dist: google-auth-oauthlib==1.2.3
Requires-Dist: googleapis-common-protos==1.72.0
Requires-Dist: greenlet==3.1.1
Requires-Dist: httplib2==0.31.0
Requires-Dist: idna==3.10
Requires-Dist: lxml==5.3.0
Requires-Dist: lxml_html_clean==0.4.1
Requires-Dist: mutagen==1.47.0
Requires-Dist: oauthlib==3.3.1
Requires-Dist: packaging==25.0
Requires-Dist: parse==1.20.2
Requires-Dist: playwright==1.49.1
Requires-Dist: proto-plus==1.26.1
Requires-Dist: protobuf==6.33.0
Requires-Dist: pyasn1==0.6.1
Requires-Dist: pyasn1_modules==0.4.2
Requires-Dist: pycryptodomex==3.23.0
Requires-Dist: pydantic==2.11.10
Requires-Dist: pydantic-settings==2.12.0
Requires-Dist: pydantic_core==2.33.2
Requires-Dist: pyee==12.0.0
Requires-Dist: pyparsing==3.2.5
Requires-Dist: pyquery==2.0.1
Requires-Dist: python-dotenv==1.2.1
Requires-Dist: requests==2.32.3
Requires-Dist: requests-htmlc==0.0.8
Requires-Dist: requests-oauthlib==2.0.0
Requires-Dist: rsa==4.9.1
Requires-Dist: soupsieve==2.6
Requires-Dist: typing-inspection==0.4.2
Requires-Dist: typing_extensions==4.12.2
Requires-Dist: uritemplate==4.2.0
Requires-Dist: urllib3==2.2.3
Requires-Dist: w3lib==2.2.1
Requires-Dist: websockets==15.0.1
Requires-Dist: yt-dlp==2025.11.12
Requires-Dist: yt-dlp-ejs==0.3.1
Provides-Extra: dev
Requires-Dist: black; extra == "dev"
Requires-Dist: click; extra == "dev"
Requires-Dist: isort; extra == "dev"
Requires-Dist: pytest; extra == "dev"
Requires-Dist: pytest-cov; extra == "dev"
Requires-Dist: mkdocs; extra == "dev"
Requires-Dist: mkdocs-material; extra == "dev"
Requires-Dist: mike; extra == "dev"
Requires-Dist: mkdocstrings-python; extra == "dev"
Provides-Extra: package
Requires-Dist: build; extra == "package"
Requires-Dist: twine; extra == "package"
Dynamic: license-file
